[
  {
    "station_id": "25951",
    "station_name": "Kg. Behor Lateh di Perlis (RHN)",
    "district": "Kangar",
    "state": "PERLIS",
    "latitude": "6.396408",
    "longitude": "100.180114",
    "main_basin": "Sungai Perlis",
    "clean_water_level": "",
    "wl_severity_level": "",
    "level": "",
    "wl_diff": "",
    "wl_date_time": "",
    "trend": "",
    "wl_type": "NO",
    "clean_rainfall": "0.5",
    "cum_daily": "11.5",
    "rf_severity_level": "Moderate",
    "rf1hour": "11.5",
    "rf3hours": "11.5",
    "rftoday": "",
    "rf24hours": "37.5",
    "rf3days": "43",
    "rf_date_time": "31/10/2025 11:15",
    "wl1_status": "",
    "rf_type": "YES",
    "rf_status": "ON",
    "alert_hour": "2",
    "wl2status": "",
    "wl3status": "",
    "stateAlert": "PERLIS",
    "wl_date_timeAlert": "",
    "rf_date_timeAlert": "31/10/2025 11:15",
    "rf_midnight": "0"
  }
]