[
  {
    "station_id": "26113",
    "station_name": "Emp. Anak Endau Pahang (RHN)",
    "district": "Rompin",
    "state": "PAHANG",
    "latitude": "2.6275",
    "longitude": "103.435278",
    "main_basin": "Sungai Endau (Pahang)",
    "clean_water_level": "-9999",
    "wl_severity_level": "Normal",
    "level": "18.8",
    "wl_diff": "-10017.8",
    "wl_date_time": "22/05/2025 20:00",
    "trend": "Rising",
    "wl_type": "YES",
    "clean_rainfall": "1",
    "cum_daily": "264.5",
    "rf_severity_level": "Heavy",
    "rf1hour": "45",
    "rf3hours": "261.5",
    "rftoday": "",
    "rf24hours": "264.5",
    "rf3days": "282.5",
    "rf_date_time": "18/10/2025 22:00",
    "wl1_status": "OFF",
    "rf_type": "YES",
    "rf_status": "ON",
    "alert_hour": "2",
    "wl2status": "OFF",
    "wl3status": "OFF",
    "stateAlert": "PAHANG",
    "wl_date_timeAlert": "",
    "rf_date_timeAlert": "18/10/2025 22:00",
    "rf_midnight": "264.5"
  },
  {
    "station_id": "25836",
    "station_name": "Rumah Rehat Lama Rompin (RHN)",
    "district": "Rompin",
    "state": "PAHANG",
    "latitude": "2.811111",
    "longitude": "103.494444",
    "main_basin": "Sungai Rompin",
    "clean_water_level": "",
    "wl_severity_level": "",
    "level": "",
    "wl_diff": "",
    "wl_date_time": "",
    "trend": "",
    "wl_type": "NO",
    "clean_rainfall": "1",
    "cum_daily": "45.5",
    "rf_severity_level": "Heavy",
    "rf1hour": "41.5",
    "rf3hours": "45",
    "rftoday": "",
    "rf24hours": "45.5",
    "rf3days": "102",
    "rf_date_time": "18/10/2025 22:00",
    "wl1_status": "",
    "rf_type": "YES",
    "rf_status": "ON",
    "alert_hour": "2",
    "wl2status": "",
    "wl3status": "",
    "stateAlert": "PAHANG",
    "wl_date_timeAlert": "",
    "rf_date_timeAlert": "18/10/2025 22:00",
    "rf_midnight": "0"
  },
  {
    "station_id": "27516",
    "station_name": "Sg. Anak Endau di Rumah Pam Setajam (F2)",
    "district": "Rompin",
    "state": "PAHANG",
    "latitude": "2.643056",
    "longitude": "103.535",
    "main_basin": "Sungai Endau (Pahang)",
    "clean_water_level": "1.42",
    "wl_severity_level": "Error",
    "level": "",
    "wl_diff": "",
    "wl_date_time": "18/10/2025 22:00",
    "trend": "Receding",
    "wl_type": "YES",
    "clean_rainfall": "1",
    "cum_daily": "63",
    "rf_severity_level": "Moderate",
    "rf1hour": "27",
    "rf3hours": "50",
    "rftoday": "",
    "rf24hours": "63",
    "rf3days": "64",
    "rf_date_time": "18/10/2025 22:00",
    "wl1_status": "ON",
    "rf_type": "YES",
    "rf_status": "ON",
    "alert_hour": "2",
    "wl2status": "NA",
    "wl3status": "OFF",
    "stateAlert": "PAHANG",
    "wl_date_timeAlert": "18/10/2025 22:00",
    "rf_date_timeAlert": "18/10/2025 22:00",
    "rf_midnight": "63"
  },
  {
    "station_id": "27521",
    "station_name": "Sg. Endau di Kastam Tg. Gemok (F2)",
    "district": "Rompin",
    "state": "PAHANG",
    "latitude": "2.660032",
    "longitude": "103.624022",
    "main_basin": "Sungai Endau (Pahang)",
    "clean_water_level": "0.16",
    "wl_severity_level": "Error",
    "level": "1",
    "wl_diff": "-0.84",
    "wl_date_time": "18/10/2025 22:00",
    "trend": "Receding",
    "wl_type": "YES",
    "clean_rainfall": "3.5",
    "cum_daily": "11",
    "rf_severity_level": "Moderate",
    "rf1hour": "11",
    "rf3hours": "11",
    "rftoday": "",
    "rf24hours": "11",
    "rf3days": "12.5",
    "rf_date_time": "18/10/2025 22:00",
    "wl1_status": "ON",
    "rf_type": "YES",
    "rf_status": "ON",
    "alert_hour": "2",
    "wl2status": "NA",
    "wl3status": "OFF",
    "stateAlert": "PAHANG",
    "wl_date_timeAlert": "18/10/2025 22:00",
    "rf_date_timeAlert": "18/10/2025 22:00",
    "rf_midnight": "11"
  },
  {
    "station_id": "27513",
    "station_name": "Sg. Rompin Di Kg. Aur (F2)",
    "district": "Rompin",
    "state": "PAHANG",
    "latitude": "3.064444",
    "longitude": "103.011667",
    "main_basin": "Sungai Rompin",
    "clean_water_level": "9.86",
    "wl_severity_level": "Error",
    "level": "",
    "wl_diff": "",
    "wl_date_time": "18/10/2025 22:00",
    "trend": "Receding",
    "wl_type": "YES",
    "clean_rainfall": "4.5",
    "cum_daily": "27",
    "rf_severity_level": "Moderate",
    "rf1hour": "27",
    "rf3hours": "27",
    "rftoday": "",
    "rf24hours": "27",
    "rf3days": "31",
    "rf_date_time": "18/10/2025 22:00",
    "wl1_status": "ON",
    "rf_type": "YES",
    "rf_status": "OFF",
    "alert_hour": "2",
    "wl2status": "NA",
    "wl3status": "OFF",
    "stateAlert": "PAHANG",
    "wl_date_timeAlert": "18/10/2025 22:00",
    "rf_date_timeAlert": "18/10/2025 22:00",
    "rf_midnight": "27"
  },
  {
    "station_id": "25877",
    "station_name": "Temeris (RHN)",
    "district": "Pekan",
    "state": "PAHANG",
    "latitude": "3.024592",
    "longitude": "103.202116",
    "main_basin": "Sg. Mercung",
    "clean_water_level": "",
    "wl_severity_level": "",
    "level": "",
    "wl_diff": "",
    "wl_date_time": "",
    "trend": "",
    "wl_type": "NO",
    "clean_rainfall": "0",
    "cum_daily": "52.5",
    "rf_severity_level": "Moderate",
    "rf1hour": "11.5",
    "rf3hours": "48.5",
    "rftoday": "",
    "rf24hours": "52.5",
    "rf3days": "78",
    "rf_date_time": "18/10/2025 22:00",
    "wl1_status": "",
    "rf_type": "YES",
    "rf_status": "ON",
    "alert_hour": "2",
    "wl2status": "",
    "wl3status": "",
    "stateAlert": "PAHANG",
    "wl_date_timeAlert": "",
    "rf_date_timeAlert": "18/10/2025 22:00",
    "rf_midnight": "0"
  },
  {
    "station_id": "25835",
    "station_name": "S.K. Leban Chondong (RHN)",
    "district": "Rompin",
    "state": "PAHANG",
    "latitude": "2.886111",
    "longitude": "103.430556",
    "main_basin": "Sungai Rompin",
    "clean_water_level": "",
    "wl_severity_level": "",
    "level": "",
    "wl_diff": "",
    "wl_date_time": "",
    "trend": "",
    "wl_type": "NO",
    "clean_rainfall": "4.5",
    "cum_daily": "23.5",
    "rf_severity_level": "Moderate",
    "rf1hour": "23",
    "rf3hours": "23",
    "rftoday": "",
    "rf24hours": "23.5",
    "rf3days": "31.5",
    "rf_date_time": "18/10/2025 22:00",
    "wl1_status": "",
    "rf_type": "YES",
    "rf_status": "ON",
    "alert_hour": "2",
    "wl2status": "",
    "wl3status": "",
    "stateAlert": "PAHANG",
    "wl_date_timeAlert": "",
    "rf_date_timeAlert": "18/10/2025 22:00",
    "rf_midnight": "0"
  },
  {
    "station_id": "25089",
    "station_name": "Stn. Per. Endau Rompin (RHN)",
    "district": "Rompin",
    "state": "PAHANG",
    "latitude": "2.8125",
    "longitude": "103.45",
    "main_basin": "Sungai Rompin",
    "clean_water_level": "",
    "wl_severity_level": "",
    "level": "",
    "wl_diff": "",
    "wl_date_time": "",
    "trend": "",
    "wl_type": "NO",
    "clean_rainfall": "2",
    "cum_daily": "10.5",
    "rf_severity_level": "Moderate",
    "rf1hour": "10.5",
    "rf3hours": "10.5",
    "rftoday": "",
    "rf24hours": "10.5",
    "rf3days": "33",
    "rf_date_time": "18/10/2025 22:00",
    "wl1_status": "NA",
    "rf_type": "YES",
    "rf_status": "ON",
    "alert_hour": "2",
    "wl2status": "NA",
    "wl3status": "NA",
    "stateAlert": "PAHANG",
    "wl_date_timeAlert": "",
    "rf_date_timeAlert": "18/10/2025 22:00",
    "rf_midnight": "0"
  },
  {
    "station_id": "2029003_",
    "station_name": "Kapit Town",
    "district": "Kapit",
    "state": "SARAWAK",
    "latitude": "2.017777",
    "longitude": "112.933722",
    "main_basin": "Batang Rajang",
    "clean_water_level": "-9999",
    "wl_severity_level": "Danger",
    "level": "15.3",
    "wl_diff": "-10014.3",
    "wl_date_time": "18/10/2025 22:15",
    "trend": "Rising",
    "wl_type": "YES",
    "clean_rainfall": "0",
    "cum_daily": "0",
    "rf_severity_level": "No Rainfall",
    "rf1hour": "0",
    "rf3hours": "0",
    "rftoday": "",
    "rf24hours": "0",
    "rf3days": "130.5",
    "rf_date_time": "18/10/2025 22:15",
    "wl1_status": "ON",
    "rf_type": "YES",
    "rf_status": "ON",
    "alert_hour": "2",
    "wl2status": "NA",
    "wl3status": "OFF",
    "stateAlert": "SARAWAK",
    "wl_date_timeAlert": "18/10/2025 22:15",
    "rf_date_timeAlert": "18/10/2025 22:15",
    "rf_midnight": "0"
  },
  {
    "station_id": "2321001_",
    "station_name": "Stapang B",
    "district": "Sibu",
    "state": "SARAWAK",
    "latitude": "2.398916",
    "longitude": "112.135833",
    "main_basin": "Batang Oya",
    "clean_water_level": "14.61",
    "wl_severity_level": "Danger",
    "level": "14.2",
    "wl_diff": "0.41",
    "wl_date_time": "18/10/2025 22:15",
    "trend": "Rising",
    "wl_type": "YES",
    "clean_rainfall": "0",
    "cum_daily": "0",
    "rf_severity_level": "No Rainfall",
    "rf1hour": "0",
    "rf3hours": "0",
    "rftoday": "",
    "rf24hours": "0",
    "rf3days": "76.5",
    "rf_date_time": "18/10/2025 22:15",
    "wl1_status": "ON",
    "rf_type": "YES",
    "rf_status": "ON",
    "alert_hour": "2",
    "wl2status": "OFF",
    "wl3status": "OFF",
    "stateAlert": "SARAWAK",
    "wl_date_timeAlert": "18/10/2025 22:15",
    "rf_date_timeAlert": "18/10/2025 22:15",
    "rf_midnight": "0"
  },
  {
    "station_id": "4448001_",
    "station_name": "Nanga Insungai",
    "district": "Limbang",
    "state": "SARAWAK",
    "latitude": "4.399269",
    "longitude": "114.895511",
    "main_basin": "Sungai Limbang",
    "clean_water_level": "8.4",
    "wl_severity_level": "Alert",
    "level": "8.2",
    "wl_diff": "0.2",
    "wl_date_time": "18/10/2025 22:15",
    "trend": "Receding",
    "wl_type": "YES",
    "clean_rainfall": "0",
    "cum_daily": "0",
    "rf_severity_level": "No Rainfall",
    "rf1hour": "0",
    "rf3hours": "0",
    "rftoday": "",
    "rf24hours": "0",
    "rf3days": "25.5",
    "rf_date_time": "18/10/2025 22:15",
    "wl1_status": "ON",
    "rf_type": "YES",
    "rf_status": "ON",
    "alert_hour": "2",
    "wl2status": "OFF",
    "wl3status": "OFF",
    "stateAlert": "SARAWAK",
    "wl_date_timeAlert": "18/10/2025 22:15",
    "rf_date_timeAlert": "18/10/2025 22:15",
    "rf_midnight": "0"
  },
  {
    "station_id": "KGDELEK",
    "station_name": "Sg. Klang di Kg. Delek",
    "district": "Klang",
    "state": "SELANGOR",
    "latitude": "3.024814",
    "longitude": "101.411081",
    "main_basin": "Sungai Klang",
    "clean_water_level": "-9999",
    "wl_severity_level": "Danger",
    "level": "1.3",
    "wl_diff": "-10000.3",
    "wl_date_time": "18/10/2025 22:15",
    "trend": "Rising",
    "wl_type": "YES",
    "clean_rainfall": "0",
    "cum_daily": "0",
    "rf_severity_level": "No Rainfall",
    "rf1hour": "0",
    "rf3hours": "0",
    "rftoday": "",
    "rf24hours": "0",
    "rf3days": "2.5",
    "rf_date_time": "18/10/2025 22:15",
    "wl1_status": "ON",
    "rf_type": "YES",
    "rf_status": "ON",
    "alert_hour": "2",
    "wl2status": "OFF",
    "wl3status": "OFF",
    "stateAlert": "SELANGOR",
    "wl_date_timeAlert": "18/10/2025 22:15",
    "rf_date_timeAlert": "18/10/2025 22:15",
    "rf_midnight": "0"
  },
  {
    "station_id": "3218101_",
    "station_name": "Sg. Langat di TNB Pangsun",
    "district": "Hulu Langat",
    "state": "SELANGOR",
    "latitude": "3.209638",
    "longitude": "101.875861",
    "main_basin": "Sungai Langat",
    "clean_water_level": "132.65",
    "wl_severity_level": "Normal",
    "level": "131.9",
    "wl_diff": "0.75",
    "wl_date_time": "18/10/2025 22:15",
    "trend": "Rising",
    "wl_type": "YES",
    "clean_rainfall": "2.5",
    "cum_daily": "38",
    "rf_severity_level": "Heavy",
    "rf1hour": "37.5",
    "rf3hours": "37.5",
    "rftoday": "",
    "rf24hours": "41",
    "rf3days": "164.5",
    "rf_date_time": "18/10/2025 22:15",
    "wl1_status": "ON",
    "rf_type": "YES",
    "rf_status": "ON",
    "alert_hour": "2",
    "wl2status": "OFF",
    "wl3status": "OFF",
    "stateAlert": "SELANGOR",
    "wl_date_timeAlert": "18/10/2025 22:15",
    "rf_date_timeAlert": "18/10/2025 22:15",
    "rf_midnight": "0"
  },
  {
    "station_id": "28026",
    "station_name": "Sg. Langat di TNB Pangsoon (F2)",
    "district": "Hulu Langat",
    "state": "SELANGOR",
    "latitude": "3.209667",
    "longitude": "101.875833",
    "main_basin": "Sungai Langat",
    "clean_water_level": "132.76",
    "wl_severity_level": "Error",
    "level": "",
    "wl_diff": "",
    "wl_date_time": "18/10/2025 22:00",
    "trend": "Rising",
    "wl_type": "YES",
    "clean_rainfall": "2.5",
    "cum_daily": "32.5",
    "rf_severity_level": "Heavy",
    "rf1hour": "32.5",
    "rf3hours": "32.5",
    "rftoday": "",
    "rf24hours": "36",
    "rf3days": "150",
    "rf_date_time": "18/10/2025 22:00",
    "wl1_status": "OFF",
    "rf_type": "YES",
    "rf_status": "ON",
    "alert_hour": "2",
    "wl2status": "OFF",
    "wl3status": "OFF",
    "stateAlert": "SELANGOR",
    "wl_date_timeAlert": "18/10/2025 22:00",
    "rf_date_timeAlert": "18/10/2025 22:00",
    "rf_midnight": "32.5"
  },
  {
    "station_id": "3017082_",
    "station_name": "Sg. Langat di Batu 12",
    "district": "Hulu Langat",
    "state": "SELANGOR",
    "latitude": "3.093388",
    "longitude": "101.797777",
    "main_basin": "Sungai Langat",
    "clean_water_level": "41.76",
    "wl_severity_level": "Alert",
    "level": "41.4",
    "wl_diff": "0.36",
    "wl_date_time": "18/10/2025 22:15",
    "trend": "Rising",
    "wl_type": "YES",
    "clean_rainfall": "0",
    "cum_daily": "0",
    "rf_severity_level": "No Rainfall",
    "rf1hour": "0",
    "rf3hours": "0",
    "rftoday": "",
    "rf24hours": "0",
    "rf3days": "8.5",
    "rf_date_time": "18/10/2025 22:15",
    "wl1_status": "ON",
    "rf_type": "YES",
    "rf_status": "ON",
    "alert_hour": "2",
    "wl2status": "OFF",
    "wl3status": "OFF",
    "stateAlert": "SELANGOR",
    "wl_date_timeAlert": "18/10/2025 22:15",
    "rf_date_timeAlert": "18/10/2025 22:15",
    "rf_midnight": "0"
  },
  {
    "station_id": "5505085_",
    "station_name": "SK Sri Pinang",
    "district": "Kuala Muda",
    "state": "KEDAH",
    "latitude": "5.595983",
    "longitude": "100.542841",
    "main_basin": "Sungai Muda",
    "clean_water_level": "",
    "wl_severity_level": "",
    "level": "",
    "wl_diff": "",
    "wl_date_time": "",
    "trend": "",
    "wl_type": "NO",
    "clean_rainfall": "32",
    "cum_daily": "32.5",
    "rf_severity_level": "Heavy",
    "rf1hour": "32",
    "rf3hours": "32",
    "rftoday": "",
    "rf24hours": "33",
    "rf3days": "132",
    "rf_date_time": "18/10/2025 22:00",
    "wl1_status": "OFF",
    "rf_type": "YES",
    "rf_status": "ON",
    "alert_hour": "2",
    "wl2status": "OFF",
    "wl3status": "OFF",
    "stateAlert": "KEDAH",
    "wl_date_timeAlert": "",
    "rf_date_timeAlert": "18/10/2025 22:00",
    "rf_midnight": "0"
  },
  {
    "station_id": "JPSMEKANIKAL",
    "station_name": "Workshop Sg. Petani",
    "district": "Kuala Muda",
    "state": "KEDAH",
    "latitude": "5.623351",
    "longitude": "100.537662",
    "main_basin": "Sungai Merbok",
    "clean_water_level": "",
    "wl_severity_level": "",
    "level": "",
    "wl_diff": "",
    "wl_date_time": "",
    "trend": "",
    "wl_type": "NO",
    "clean_rainfall": "11.5",
    "cum_daily": "11.5",
    "rf_severity_level": "Moderate",
    "rf1hour": "11.5",
    "rf3hours": "11.5",
    "rftoday": "",
    "rf24hours": "11.5",
    "rf3days": "11.5",
    "rf_date_time": "18/10/2025 22:00",
    "wl1_status": "NA",
    "rf_type": "YES",
    "rf_status": "ON",
    "alert_hour": "2",
    "wl2status": "NA",
    "wl3status": "NA",
    "stateAlert": "KEDAH",
    "wl_date_timeAlert": "",
    "rf_date_timeAlert": "18/10/2025 22:00",
    "rf_midnight": "0"
  },
  {
    "station_id": "26331",
    "station_name": "Workshop Sg. Petani (RHN)",
    "district": "Kuala Muda",
    "state": "KEDAH",
    "latitude": "5.623345",
    "longitude": "100.537664",
    "main_basin": "Sungai Muda",
    "clean_water_level": "",
    "wl_severity_level": "",
    "level": "",
    "wl_diff": "",
    "wl_date_time": "",
    "trend": "",
    "wl_type": "NO",
    "clean_rainfall": "0.5",
    "cum_daily": "11.5",
    "rf_severity_level": "Moderate",
    "rf1hour": "11.5",
    "rf3hours": "11.5",
    "rftoday": "",
    "rf24hours": "12",
    "rf3days": "52.5",
    "rf_date_time": "18/10/2025 22:00",
    "wl1_status": "",
    "rf_type": "YES",
    "rf_status": "ON",
    "alert_hour": "2",
    "wl2status": "",
    "wl3status": "",
    "stateAlert": "KEDAH",
    "wl_date_timeAlert": "",
    "rf_date_timeAlert": "18/10/2025 22:00",
    "rf_midnight": "0"
  },
  {
    "station_id": "SG MUAR",
    "station_name": "Sg. Kesang di Telok Rimba",
    "district": "Tangkak",
    "state": "JOHOR",
    "latitude": "2.173816",
    "longitude": "102.503032",
    "main_basin": "Sungai Kesang (Johor)",
    "clean_water_level": "2.98",
    "wl_severity_level": "Alert",
    "level": "2.5",
    "wl_diff": "0.48",
    "wl_date_time": "18/10/2025 22:00",
    "trend": "No Change",
    "wl_type": "YES",
    "clean_rainfall": "0",
    "cum_daily": "2",
    "rf_severity_level": "No Rainfall",
    "rf1hour": "0",
    "rf3hours": "0",
    "rftoday": "",
    "rf24hours": "2",
    "rf3days": "42",
    "rf_date_time": "18/10/2025 22:00",
    "wl1_status": "ON",
    "rf_type": "YES",
    "rf_status": "ON",
    "alert_hour": "2",
    "wl2status": "OFF",
    "wl3status": "OFF",
    "stateAlert": "JOHOR",
    "wl_date_timeAlert": "18/10/2025 22:00",
    "rf_date_timeAlert": "18/10/2025 22:00",
    "rf_midnight": "0"
  },
  {
    "station_id": "SILICA",
    "station_name": "Johor Silica",
    "district": "Kota Tinggi",
    "state": "JOHOR",
    "latitude": "1.562705",
    "longitude": "104.182789",
    "main_basin": "Sungai Lebam",
    "clean_water_level": "",
    "wl_severity_level": "",
    "level": "",
    "wl_diff": "",
    "wl_date_time": "",
    "trend": "",
    "wl_type": "NO",
    "clean_rainfall": "9",
    "cum_daily": "16",
    "rf_severity_level": "Moderate",
    "rf1hour": "16",
    "rf3hours": "16",
    "rftoday": "",
    "rf24hours": "16",
    "rf3days": "25",
    "rf_date_time": "18/10/2025 22:00",
    "wl1_status": "",
    "rf_type": "YES",
    "rf_status": "ON",
    "alert_hour": "2",
    "wl2status": "",
    "wl3status": "",
    "stateAlert": "JOHOR",
    "wl_date_timeAlert": "",
    "rf_date_timeAlert": "18/10/2025 22:00",
    "rf_midnight": "0"
  },
  {
    "station_id": "WAKSALAM",
    "station_name": "Loji Air Wak Salam",
    "district": "Mersing",
    "state": "JOHOR",
    "latitude": "2.3416",
    "longitude": "103.81851",
    "main_basin": "Sungai Mersing",
    "clean_water_level": "",
    "wl_severity_level": "",
    "level": "",
    "wl_diff": "",
    "wl_date_time": "",
    "trend": "",
    "wl_type": "NO",
    "clean_rainfall": "24",
    "cum_daily": "30",
    "rf_severity_level": "Moderate",
    "rf1hour": "30",
    "rf3hours": "30",
    "rftoday": "",
    "rf24hours": "30",
    "rf3days": "32",
    "rf_date_time": "18/10/2025 22:00",
    "wl1_status": "OFF",
    "rf_type": "YES",
    "rf_status": "ON",
    "alert_hour": "2",
    "wl2status": "OFF",
    "wl3status": "OFF",
    "stateAlert": "JOHOR",
    "wl_date_timeAlert": "",
    "rf_date_timeAlert": "18/10/2025 22:00",
    "rf_midnight": "0"
  },
  {
    "station_id": "2636170_",
    "station_name": "Stor JPS Endau",
    "district": "Mersing",
    "state": "JOHOR",
    "latitude": "2.647292",
    "longitude": "103.619125",
    "main_basin": "Sungai Endau",
    "clean_water_level": "",
    "wl_severity_level": "",
    "level": "",
    "wl_diff": "",
    "wl_date_time": "",
    "trend": "",
    "wl_type": "NO",
    "clean_rainfall": "9",
    "cum_daily": "15",
    "rf_severity_level": "Moderate",
    "rf1hour": "15",
    "rf3hours": "15",
    "rftoday": "",
    "rf24hours": "15",
    "rf3days": "15",
    "rf_date_time": "18/10/2025 22:00",
    "wl1_status": "OFF",
    "rf_type": "YES",
    "rf_status": "ON",
    "alert_hour": "2",
    "wl2status": "OFF",
    "wl3status": "OFF",
    "stateAlert": "JOHOR",
    "wl_date_timeAlert": "",
    "rf_date_timeAlert": "18/10/2025 22:00",
    "rf_midnight": "0"
  },
  {
    "station_id": "5411066_",
    "station_name": "Sg. Perak di Kuala Kenderong",
    "district": "Hulu Perak",
    "state": "PERAK",
    "latitude": "5.416667",
    "longitude": "101.154167",
    "main_basin": "Sungai Perak",
    "clean_water_level": "110.63",
    "wl_severity_level": "Normal",
    "level": "110",
    "wl_diff": "0.63",
    "wl_date_time": "18/10/2025 22:00",
    "trend": "Rising",
    "wl_type": "YES",
    "clean_rainfall": "5.5",
    "cum_daily": "75",
    "rf_severity_level": "Moderate",
    "rf1hour": "16",
    "rf3hours": "39.5",
    "rftoday": "",
    "rf24hours": "75",
    "rf3days": "100",
    "rf_date_time": "18/10/2025 22:00",
    "wl1_status": "ON",
    "rf_type": "YES",
    "rf_status": "ON",
    "alert_hour": "2",
    "wl2status": "NA",
    "wl3status": "NA",
    "stateAlert": "PERAK",
    "wl_date_timeAlert": "18/10/2025 22:00",
    "rf_date_timeAlert": "18/10/2025 22:00",
    "rf_midnight": "0"
  },
  {
    "station_id": "3023098_",
    "station_name": "Sg. Lui",
    "district": "Jempol",
    "state": "NEGERI SEMBILAN",
    "latitude": "3.08394",
    "longitude": "102.36582",
    "main_basin": "Sungai Pahang (NS)",
    "clean_water_level": "",
    "wl_severity_level": "",
    "level": "",
    "wl_diff": "",
    "wl_date_time": "",
    "trend": "",
    "wl_type": "NO",
    "clean_rainfall": "28",
    "cum_daily": "29.5",
    "rf_severity_level": "Moderate",
    "rf1hour": "28",
    "rf3hours": "28",
    "rftoday": "",
    "rf24hours": "36.5",
    "rf3days": "38.5",
    "rf_date_time": "18/10/2025 22:00",
    "wl1_status": "OFF",
    "rf_type": "YES",
    "rf_status": "ON",
    "alert_hour": "2",
    "wl2status": "OFF",
    "wl3status": "OFF",
    "stateAlert": "NEGERI SEMBILAN",
    "wl_date_timeAlert": "",
    "rf_date_timeAlert": "18/10/2025 22:00",
    "rf_midnight": "0"
  },
  {
    "station_id": "_NKPH0002",
    "station_name": "Sg. Lui Halt (F1)",
    "district": "Jempol",
    "state": "NEGERI SEMBILAN",
    "latitude": "3.084722",
    "longitude": "102.369444",
    "main_basin": "Sungai Pahang (NS)",
    "clean_water_level": "",
    "wl_severity_level": "",
    "level": "",
    "wl_diff": "",
    "wl_date_time": "",
    "trend": "",
    "wl_type": "NO",
    "clean_rainfall": "1",
    "cum_daily": "28.5",
    "rf_severity_level": "Moderate",
    "rf1hour": "27",
    "rf3hours": "27",
    "rftoday": "",
    "rf24hours": "43.5",
    "rf3days": "58",
    "rf_date_time": "18/10/2025 22:00",
    "wl1_status": "OFF",
    "rf_type": "YES",
    "rf_status": "ON",
    "alert_hour": "2",
    "wl2status": "OFF",
    "wl3status": "OFF",
    "stateAlert": "NEGERI SEMBILAN",
    "wl_date_timeAlert": "",
    "rf_date_timeAlert": "18/10/2025 22:00",
    "rf_midnight": "0"
  },
  {
    "station_id": "5405001_",
    "station_name": "Sg. Kulim di Ara Kuda",
    "district": "Seberang Perai Tengah",
    "state": "PULAU PINANG",
    "latitude": "5.435391",
    "longitude": "100.511837",
    "main_basin": "Sungai Perai",
    "clean_water_level": "-9999",
    "wl_severity_level": "Danger",
    "level": "8.1",
    "wl_diff": "-10007.1",
    "wl_date_time": "18/10/2025 22:00",
    "trend": "Rising",
    "wl_type": "YES",
    "clean_rainfall": "0",
    "cum_daily": "0",
    "rf_severity_level": "No Rainfall",
    "rf1hour": "0",
    "rf3hours": "0",
    "rftoday": "",
    "rf24hours": "0",
    "rf3days": "45.5",
    "rf_date_time": "18/10/2025 22:00",
    "wl1_status": "ON",
    "rf_type": "YES",
    "rf_status": "ON",
    "alert_hour": "2",
    "wl2status": "OFF",
    "wl3status": "OFF",
    "stateAlert": "PULAU PINANG",
    "wl_date_timeAlert": "18/10/2025 22:00",
    "rf_date_timeAlert": "18/10/2025 22:00",
    "rf_midnight": "0"
  },
  {
    "station_id": "_DGMG0002",
    "station_name": "Belatop (F1)",
    "district": "Gua Musang",
    "state": "KELANTAN",
    "latitude": "4.66106",
    "longitude": "101.48525",
    "main_basin": "Sungai Kelantan",
    "clean_water_level": "610.1",
    "wl_severity_level": "Error",
    "level": "605.5",
    "wl_diff": "4.6",
    "wl_date_time": "18/10/2025 22:00",
    "trend": "No Change",
    "wl_type": "YES",
    "clean_rainfall": "0.5",
    "cum_daily": "24",
    "rf_severity_level": "Moderate",
    "rf1hour": "17",
    "rf3hours": "21",
    "rftoday": "",
    "rf24hours": "24.5",
    "rf3days": "25",
    "rf_date_time": "18/10/2025 22:00",
    "wl1_status": "OFF",
    "rf_type": "YES",
    "rf_status": "ON",
    "alert_hour": "2",
    "wl2status": "ON",
    "wl3status": "OFF",
    "stateAlert": "KELANTAN",
    "wl_date_timeAlert": "18/10/2025 22:00",
    "rf_date_timeAlert": "18/10/2025 22:00",
    "rf_midnight": "24"
  }
]